ByCap/__init__.py
ByCap/base.py
ByCap/compat.py
ByCap/exceptions.py
ByCap/tasks.py
ByCap-0.1.0.dist-info/METADATA
ByCap-0.1.0.dist-info/WHEEL
ByCap-0.1.0.dist-info/top_level.txt
ByCap-0.1.0.dist-info/RECORD
