Metadata-Version: 2.1
Name: ByCap
Version: 0.1.0
Summary: A simple python library that bypasses captchas.
Home-page: 
Author: Jiro
Author-email: contact@jiroawesome.tech
License: MIT
